LICENSE
README.md
setup.cfg
setup.py
promptsource/__init__.py
promptsource/app.py
promptsource/session.py
promptsource/templates.py
promptsource/utils.py
promptsource.egg-info/PKG-INFO
promptsource.egg-info/SOURCES.txt
promptsource.egg-info/dependency_links.txt
promptsource.egg-info/requires.txt
promptsource.egg-info/top_level.txt
promptsource/templates/Zaid/coqa_expanded/templates.yaml
promptsource/templates/Zaid/quac_expanded/templates.yaml
promptsource/templates/acronym_identification/templates.yaml
promptsource/templates/ade_corpus_v2/Ade_corpus_v2_classification/templates.yaml
promptsource/templates/ade_corpus_v2/Ade_corpus_v2_drug_ade_relation/templates.yaml
promptsource/templates/ade_corpus_v2/Ade_corpus_v2_drug_dosage_relation/templates.yaml
promptsource/templates/adversarial_qa/adversarialQA/templates.yaml
promptsource/templates/adversarial_qa/dbert/templates.yaml
promptsource/templates/adversarial_qa/dbidaf/templates.yaml
promptsource/templates/adversarial_qa/droberta/templates.yaml
promptsource/templates/aeslc/templates.yaml
promptsource/templates/ag_news/templates.yaml
promptsource/templates/ai2_arc/ARC-Challenge/templates.yaml
promptsource/templates/ai2_arc/ARC-Easy/templates.yaml
promptsource/templates/amazon_polarity/templates.yaml
promptsource/templates/amazon_reviews_multi/en/templates.yaml
promptsource/templates/amazon_us_reviews/Wireless_v1_00/templates.yaml
promptsource/templates/ambig_qa/light/templates.yaml
promptsource/templates/anli/templates.yaml
promptsource/templates/app_reviews/templates.yaml
promptsource/templates/aqua_rat/raw/templates.yaml
promptsource/templates/art/templates.yaml
promptsource/templates/asnq/templates.yaml
promptsource/templates/asset/ratings/templates.yaml
promptsource/templates/asset/simplification/templates.yaml
promptsource/templates/banking77/templates.yaml
promptsource/templates/billsum/templates.yaml
promptsource/templates/bing_coronavirus_query_set/templates.yaml
promptsource/templates/biosses/templates.yaml
promptsource/templates/blbooksgenre/title_genre_classifiction/templates.yaml
promptsource/templates/blended_skill_talk/templates.yaml
promptsource/templates/cbt/CN/templates.yaml
