Metadata-Version: 2.1
Name: promptsource
Version: 0.2.3
Summary: An Integrated Development Environment and Repository for Natural Language Prompts.
Home-page: https://github.com/bigscience-workshop/promptsource.git
Author: BigScience - Prompt Engineering Working Group
Author-email: sbach@cs.brown.edu,victor@huggingface.co
License: Apache Software License 2.0
Platform: UNKNOWN
Classifier: Development Status :: 2 - Pre-Alpha
Classifier: Intended Audience :: Developers
Classifier: License :: OSI Approved :: Apache Software License
Classifier: Natural Language :: English
Classifier: Programming Language :: Python :: 3
Classifier: Programming Language :: Python :: 3.7
Classifier: Programming Language :: Python :: 3.8
Classifier: Programming Language :: Python :: 3.9
Requires-Python: >=3.7,<3.10
License-File: LICENSE
